pyriddles/__init__.py
pyriddles/__main__.py
pyriddles/cli.py
pyriddles/config.py
pyriddles/example_usage.py
pyriddles/hints.py
pyriddles-0.0.2.dist-info/licenses/LICENSE
pyriddles-0.0.2.dist-info/METADATA
pyriddles-0.0.2.dist-info/WHEEL
pyriddles-0.0.2.dist-info/entry_points.txt
pyriddles-0.0.2.dist-info/top_level.txt
pyriddles-0.0.2.dist-info/RECORD
