Metadata-Version: 2.4
Name: pyriddles
Version: 0.0.2
Summary: A python riddles package.
Author-email: Kahmeeah Obey <kahmeeah@nyu.edu>, Gabriella Codrington <gc1855@nyu.edu>, Jahleel Townsend <jlt9287@nyu.edu>, Matthew Ortega <mro9388@nyu.edu>
License:                     GNU GENERAL PUBLIC LICENSE
Project-URL: Homepage, https://github.com/software-students-spring2025/3-python-package-gmjm
Project-URL: Repository, https://github.com/software-students-spring2025/3-python-package-gmjm.git
Project-URL: Bug Tracker, https://github.com/software-students-spring2025/3-python-package-gmjm/issues
Keywords: python,package,build,riddles,fun
Classifier: Programming Language :: Python :: 3
Classifier: Intended Audience :: Education
Classifier: License :: OSI Approved :: GNU General Public License v3 (GPLv3)
Classifier: Operating System :: OS Independent
Requires-Python: >=3.7
License-File: LICENSE
Provides-Extra: dev
Requires-Dist: pytest; extra == "dev"
Dynamic: license-file
